LICENSE
README.md
ekspress/__init__.py
ekspress/__main__.py
ekspress/cli.py
ekspress-0.0.0.dist-info/LICENSE
ekspress-0.0.0.dist-info/METADATA
ekspress-0.0.0.dist-info/WHEEL
ekspress-0.0.0.dist-info/entry_points.txt
ekspress-0.0.0.dist-info/RECORD
